ciftify/__init__.py
ciftify/config.py
ciftify/filenames.py
ciftify/html.py
ciftify/meants.py
ciftify/niio.py
ciftify/qc_config.py
ciftify/report.py
ciftify/utils.py
ciftify/bidsapp/__init__.py
ciftify/bidsapp/fmriprep_ciftify.py
ciftify/bin/__init__.py
ciftify/bin/cifti_vis_PINT
ciftify/bin/cifti_vis_PINT.py
ciftify/bin/cifti_vis_RSN
ciftify/bin/cifti_vis_fmri
ciftify/bin/cifti_vis_fmri.py
ciftify/bin/cifti_vis_map
ciftify/bin/cifti_vis_map.py
ciftify/bin/cifti_vis_recon_all
ciftify/bin/cifti_vis_recon_all.py
ciftify/bin/ciftify_PINT_vertices
ciftify/bin/ciftify_PINT_vertices.py
ciftify/bin/ciftify_atlas_report
ciftify/bin/ciftify_atlas_report.py
ciftify/bin/ciftify_clean_img
ciftify/bin/ciftify_clean_img.py
ciftify/bin/ciftify_dlabel_to_vol
ciftify/bin/ciftify_dlabel_to_vol.py
ciftify/bin/ciftify_falff
ciftify/bin/ciftify_falff.py
ciftify/bin/ciftify_groupmask
ciftify/bin/ciftify_groupmask.py
ciftify/bin/ciftify_meants
ciftify/bin/ciftify_meants.py
ciftify/bin/ciftify_peaktable
ciftify/bin/ciftify_peaktable.py
ciftify/bin/ciftify_postPINT1_concat
ciftify/bin/ciftify_postPINT1_concat.py
ciftify/bin/ciftify_postPINT2_sub2sub
ciftify/bin/ciftify_postPINT2_sub2sub.py
ciftify/bin/ciftify_recon_all
ciftify/bin/ciftify_recon_all.py
ciftify/bin/ciftify_seed_corr
ciftify/bin/ciftify_seed_corr.py
ciftify/bin/ciftify_statclust_report
ciftify/bin/ciftify_statclust_report.py
ciftify/bin/ciftify_subject_fmri
ciftify/bin/ciftify_subject_fmri.py
ciftify/bin/ciftify_surface_rois
ciftify/bin/ciftify_surface_rois.py
ciftify/bin/ciftify_vol_result
ciftify/bin/ciftify_vol_result.py
ciftify/bin/epi_hcpexport
ciftify/bin/extract_nuisance_regressors
ciftify/bin/extract_nuisance_regressors.py
ciftify/bin/filter_hcp.sh
ciftify/bin/logging.conf
ciftify/data/ciftify_workflow_settings.yaml
ciftify/data/qc_modes.yaml
ciftify/data/91282_Greyordinates/91282_Greyordinates.dscalar.nii
ciftify/data/91282_Greyordinates/Atlas_ROIs.2.nii.gz
ciftify-2.3.3.dist-info/LICENSE
ciftify-2.3.3.dist-info/METADATA
ciftify-2.3.3.dist-info/WHEEL
ciftify-2.3.3.dist-info/entry_points.txt
ciftify-2.3.3.dist-info/top_level.txt
ciftify-2.3.3.dist-info/RECORD
