Metadata-Version: 2.1
Name: ciftify
Version: 2.3.3
Summary: The tools of the Human Connectome Project (HCP) adapted for working with non-HCP datasets
Home-page: https://github.com/edickie/ciftify
Author: Erin W.E. Dickie
Author-email: erin.w.dickie@gmail.com
License: MIT
Keywords: PINT neuroimaging fMRI cifti gifti nifti HCP
Platform: UNKNOWN
Classifier: Development Status :: 4 - Beta
Classifier: Intended Audience :: Science/Research
Classifier: License :: OSI Approved :: MIT License
Classifier: Natural Language :: English
Classifier: Operating System :: POSIX :: Linux
Classifier: Programming Language :: Python :: 3
Requires-Dist: docopt
Requires-Dist: matplotlib
Requires-Dist: nibabel
Requires-Dist: numpy
Requires-Dist: pandas
Requires-Dist: PyYaml
Requires-Dist: seaborn
Requires-Dist: scipy
Requires-Dist: pillow
Requires-Dist: nilearn
Requires-Dist: scikit-learn
Requires-Dist: pybids (>=0.7.0)
